{
  "openapi": "3.1.0",
  "info": {
    "version": "1.0.0",
    "title": "Contacts App",
    "license": {
      "name": "Apache 2.0",
      "url": "http://www.apache.org/licenses/LICENSE-2.0.html"
    },
    "description": "This is a documentation of Contacts App"
  },
  "servers": [
    {
      "url": "http://localhost:3000"
    },
    {
      "url": "https://contacts-app-1b4a.onrender.com"
    }
  ],
  "tags": [
    {
      "name": "Contacts",
      "description": "Operations about users."
    }
  ],
  "paths": {
    "/contacts": {
      "get": {
        "tags": [
          "Contacts"
        ],
        "summary": "Get list of all contacts by a user",
        "operationId": "getAllContacts",
        "description": "Get list of all contacts by a user",
        "security": [
          {
            "bearerAuth": []
          }
        ],
        "parameters": [
          {
            "in": "query",
            "name": "page",
            "schema": {
              "type": "integer",
              "example": 1
            }
          },
          {
            "in": "query",
            "name": "perPage",
            "schema": {
              "type": "integer",
              "example": 10
            }
          },
          {
            "in": "query",
            "name": "sortBy",
            "schema": {
              "type": "string",
              "example": "name"
            },
            "description": "All contact's fields can be mentioned. Default value - _id"
          },
          {
            "in": "query",
            "name": "sortOrder",
            "schema": {
              "type": "string",
              "enum": [
                "asc",
                "desc"
              ],
              "example": "asc"
            }
          }
        ],
        "responses": {
          "200": {
            "description": "Successfully found contacts",
            "content": {
              "application/json": {
                "schema": {
                  "type": "object",
                  "required": [
                    "status",
                    "message",
                    "data"
                  ],
                  "properties": {
                    "status": {
                      "type": "integer",
                      "example": 200
                    },
                    "message": {
                      "type": "string",
                      "example": "Successfully found contacts"
                    },
                    "data": {
                      "type": "object",
                      "required": [
                        "data",
                        "page",
                        "perPage",
                        "totalItems",
                        "totalPages",
                        "hasPreviousPage",
                        "hasNextPage"
                      ],
                      "properties": {
                        "page": {
                          "type": "integer",
                          "example": 1
                        },
                        "perPage": {
                          "type": "integer",
                          "example": 10
                        },
                        "totalItems": {
                          "type": "integer",
                          "example": 100
                        },
                        "totalPages": {
                          "type": "integer",
                          "example": 10
                        },
                        "hasPreviousPage": {
                          "type": "boolean",
                          "example": false
                        },
                        "hasNextPage": {
                          "type": "boolean",
                          "example": true
                        },
                        "contacts": {
                          "type": "array",
                          "items": {
                            "$ref": "#/components/schemas/contact"
                          }
                        }
                      }
                    }
                  }
                }
              }
            }
          },
          "401": {
            "$ref": "#/components/responses/401"
          },
          "500": {
            "$ref": "#/components/responses/500"
          }
        }
      },
      "post": {
        "tags": [
          "Contacts"
        ],
        "summary": "Create a contact",
        "operationId": "createContact",
        "description": "Create a contact",
        "security": [
          {
            "bearerAuth": []
          }
        ],
        "requestBody": {
          "content": {
            "multipart/form-data": {
              "schema": {
                "type": "object",
                "required": [
                  "name",
                  "phoneNumber",
                  "contactType"
                ],
                "properties": {
                  "name": {
                    "description": "Contact's name",
                    "type": "string",
                    "example": "John Doe"
                  },
                  "phoneNumber": {
                    "description": "Contact's phone number",
                    "type": "string",
                    "example": "+3800000000010"
                  },
                  "email": {
                    "description": "Contact's email",
                    "type": "string",
                    "example": "example@gmail.com"
                  },
                  "isFavourite": {
                    "description": "Contact's choice",
                    "type": "boolean",
                    "example": false
                  },
                  "contactType": {
                    "description": "Contact's type",
                    "type": "string",
                    "enum": [
                      "work",
                      "home",
                      "personal"
                    ]
                  },
                  "photo": {
                    "description": "Contact's photo",
                    "type": "string",
                    "format": "binary"
                  }
                }
              }
            }
          }
        },
        "responses": {
          "201": {
            "description": "Creates a student",
            "content": {
              "application/json": {
                "schema": {
                  "type": "object",
                  "required": [
                    "status",
                    "message",
                    "data"
                  ],
                  "properties": {
                    "status": {
                      "type": "integer",
                      "example": 201
                    },
                    "message": {
                      "type": "string",
                      "example": "Successfully created a student!"
                    },
                    "data": {
                      "type": "object",
                      "$ref": "#/components/schemas/contact"
                    }
                  }
                }
              }
            }
          },
          "401": {
            "$ref": "#/components/responses/401"
          },
          "500": {
            "$ref": "#/components/responses/500"
          }
        }
      }
    },
    "/contacts/{id}": {
      "patch": {
        "tags": [
          "Contacts"
        ],
        "summary": "Update a contact by ID",
        "operationId": "updateContact",
        "description": "Update appropriate data of a specific contact using the contact`s ID.",
        "security": [
          {
            "bearerAuth": []
          }
        ],
        "parameters": [
          {
            "name": "id",
            "in": "path",
            "required": true,
            "description": "ID of the contact to update",
            "schema": {
              "type": "string",
              "example": "67797d2c19cd6ca651b0dcd7"
            }
          }
        ],
        "requestBody": {
          "required": true,
          "content": {
            "multipart/form-data": {
              "schema": {
                "type": "object",
                "properties": {
                  "name": {
                    "description": "Name of the contact",
                    "type": "string",
                    "example": "John Doe"
                  },
                  "phoneNumber": {
                    "description": "Phone number of the contact",
                    "type": "string",
                    "example": 3800000000010
                  },
                  "email": {
                    "description": "Email address of the contact",
                    "type": "string",
                    "example": "example@gmail.com"
                  },
                  "isFavourite": {
                    "description": "Whether the contact is a favorite or not",
                    "type": "boolean",
                    "example": true
                  },
                  "contactType": {
                    "description": "Type of the contact (personal, work, home)",
                    "type": "string",
                    "example": "personal",
                    "enum": [
                      "personal",
                      "work",
                      "home"
                    ]
                  },
                  "photo": {
                    "description": "Photo of the contact",
                    "type": "string",
                    "format": "binary"
                  }
                }
              }
            }
          }
        },
        "responses": {
          "200": {
            "description": "Contact updated successfully",
            "content": {
              "application/json": {
                "schema": {
                  "type": "object",
                  "required": [
                    "status",
                    "message",
                    "data"
                  ],
                  "properties": {
                    "status": {
                      "type": "integer",
                      "example": 200
                    },
                    "message": {
                      "type": "string",
                      "example": "Contact updated successfully"
                    },
                    "data": {
                      "type": "object",
                      "$ref": "#/components/schemas/contact"
                    }
                  }
                }
              }
            }
          },
          "401": {
            "$ref": "#/components/responses/401"
          },
          "404": {
            "$ref": "#/components/responses/404"
          },
          "500": {
            "$ref": "#/components/responses/500"
          }
        }
      },
      "delete": {
        "tags": [
          "Contacts"
        ],
        "summary": "Delete a contact by ID",
        "operationId": "deleteContact",
        "description": "Remove a specific contact from the database using the contact`s ID.",
        "security": [
          {
            "bearerAuth": []
          }
        ],
        "parameters": [
          {
            "name": "id",
            "in": "path",
            "required": true,
            "description": "ID of the contact to delete",
            "schema": {
              "type": "string",
              "example": "67797d2c19cd6ca651b0dcd7"
            }
          }
        ],
        "responses": {
          "204": {
            "description": "Contact deleted successfully"
          },
          "401": {
            "$ref": "#/components/responses/401"
          },
          "404": {
            "$ref": "#/components/responses/404"
          },
          "500": {
            "$ref": "#/components/responses/500"
          }
        }
      },
      "get": {
        "tags": [
          "Contacts"
        ],
        "summary": "Get a contact by ID",
        "operationId": "getContactById",
        "description": "Get a contact by ID",
        "security": [
          {
            "bearerAuth": []
          }
        ],
        "parameters": [
          {
            "in": "path",
            "name": "id",
            "required": true,
            "schema": {
              "type": "string",
              "example": "67797d2c19cd6ca651b0dcd7"
            }
          }
        ],
        "responses": {
          "200": {
            "description": "Get contact by ID",
            "content": {
              "application/json": {
                "schema": {
                  "type": "object",
                  "required": [
                    "status",
                    "message",
                    "data"
                  ],
                  "properties": {
                    "status": {
                      "type": "integer",
                      "example": 200
                    },
                    "message": {
                      "type": "string",
                      "example": "Successfully found contact with id 67797d2c19cd6ca651b0dcd7!"
                    },
                    "data": {
                      "type": "object",
                      "$ref": "#/components/schemas/contact"
                    }
                  }
                }
              }
            }
          },
          "401": {
            "$ref": "#/components/responses/401"
          },
          "404": {
            "$ref": "#/components/responses/404"
          },
          "500": {
            "$ref": "#/components/responses/500"
          }
        }
      }
    }
  },
  "components": {
    "securitySchemes": {
      "bearerAuth": {
        "type": "http",
        "scheme": "bearer"
      }
    },
    "schemas": {
      "contact": {
        "type": "object",
        "required": [
          "_id",
          "name",
          "phoneNumber",
          "contactType",
          "userId"
        ],
        "properties": {
          "_id": {
            "description": "Contact's id",
            "type": "string",
            "example": "67797d2c19cd6ca651b0dcd7"
          },
          "name": {
            "description": "Contact's name",
            "type": "string",
            "example": "John Doe"
          },
          "phoneNumber": {
            "description": "Contact's phone number",
            "type": "string",
            "example": "+3800000000010"
          },
          "email": {
            "description": "Contact's email",
            "type": "string",
            "example": "example@gmail.com"
          },
          "isFavourite": {
            "description": "Whether the contact is a favorite or not",
            "type": "boolean",
            "example": false
          },
          "contactType": {
            "description": "Contact's type",
            "type": "string",
            "enum": [
              "work",
              "home",
              "personal"
            ]
          },
          "userId": {
            "description": "Contact's user id",
            "type": "string",
            "example": "67797ce719cd6ca651b0dcc6"
          },
          "photo": {
            "description": "Link to contact's photo",
            "type": "string",
            "example": "https://res.cloudinary.com/dcbxja7w4/image/upload/v1736015161/seogiqwlqvylrs6ptiww.jpg"
          },
          "createdAt": {
            "description": "Timestamp for tracking when the contact was created",
            "type": "string",
            "format": "date-time",
            "example": "2025-01-03T12:35:48.749+00:00"
          },
          "updatedAt": {
            "description": "Timestamp for tracking when the contact was updated the last time",
            "type": "string",
            "format": "date-time",
            "example": "2025-01-03T12:35:48.749+00:00"
          }
        }
      }
    },
    "responses": {
      "401": {
        "description": "Unauthorized error",
        "content": {
          "application/json": {
            "schema": {
              "type": "object",
              "required": [
                "status",
                "message",
                "data"
              ],
              "properties": {
                "status": {
                  "type": "integer",
                  "example": 401
                },
                "message": {
                  "type": "string",
                  "example": "UnauthorizedError"
                },
                "data": {
                  "type": "object",
                  "required": [
                    "message"
                  ],
                  "properties": {
                    "message": {
                      "type": "string",
                      "example": "Access token expired"
                    }
                  }
                }
              }
            }
          }
        }
      },
      "404": {
        "description": "Contact not found",
        "content": {
          "application/json": {
            "schema": {
              "type": "object",
              "required": [
                "status",
                "message"
              ],
              "properties": {
                "status": {
                  "type": "integer",
                  "example": 404
                },
                "message": {
                  "type": "string",
                  "example": "Not found"
                }
              }
            }
          }
        }
      },
      "500": {
        "description": "Internal server error",
        "content": {
          "application/json": {
            "schema": {
              "type": "object",
              "required": [
                "status",
                "message"
              ],
              "properties": {
                "status": {
                  "type": "integer",
                  "example": 500
                },
                "message": {
                  "type": "string",
                  "example": "Internal server error"
                }
              }
            }
          }
        }
      }
    }
  }
}